facit/__init__.py
facit/components.py
facit/constants.py
facit/io.py
facit/modelling.py
facit/processing.py
facit/recording.py
facit/testing.py
facit/_pyinstaller_hooks/__init__.py
facit/_pyinstaller_hooks/conftest.py
facit/_pyinstaller_hooks/stdhooks/hook-OCP.py
facit/_pyinstaller_hooks/stdhooks/hook-cadquery.py
facit/_pyinstaller_hooks/stdhooks/hook-openmdao.py
facit/_pyinstaller_hooks/stdhooks/hook-vtk.py
facit-0.3.0.dist-info/METADATA
facit-0.3.0.dist-info/WHEEL
facit-0.3.0.dist-info/entry_points.txt
facit-0.3.0.dist-info/licenses/LICENSE
facit-0.3.0.dist-info/RECORD
