Metadata-Version: 2.1
Name: facit
Version: 0.3.0
Project-URL: Homepage, https://github.com/ovidner/facit
Author: Camilla Wehlin, Anton Wiberg
Author-email: Olle Vidner <olle@vidner.se>
Maintainer-email: Olle Vidner <olle@vidner.se>
License-Expression: MIT
License-File: LICENSE
Requires-Python: >=3.9
Requires-Dist: jsonpickle
Requires-Dist: numpy
Requires-Dist: openmdao
Requires-Dist: pandas
Requires-Dist: pydantic
Requires-Dist: pydoe2
Requires-Dist: xarray
Requires-Dist: zarr
Provides-Extra: test
Requires-Dist: deepdiff; extra == 'test'
Requires-Dist: hypothesis; extra == 'test'
Requires-Dist: pytest; extra == 'test'
